New Version/FPGA_withLoop/look_up_table_interconnect_config.v
module look_up_table_interconnect_config(bit_in,prgm_b,clk,reset,lut,CLB_prgm_b,CLB_prgm_b_in,CLB_prgm_b_out,
  interconnect_config_x1,interconnect_config_x2,interconnect_config_x3,interconnect_config_x4,mux_switch);
input bit_in,prgm_b,clk,reset,CLB_prgm_b,CLB_prgm_b_in;
reg q15,q14,q13,q12,q11,q10,q9,q8,q7,q6,q5,q4,q3,q2,q1,q0,
i_q19,i_q18,i_q17,i_q16,i_q15,i_q14,i_q13,i_q12,i_q11,i_q10,i_q9,i_q8,i_q7,i_q6,i_q5,i_q4,i_q3,i_q2,i_q1,i_q0,switch;
output reg mux_switch,CLB_prgm_b_out;
output reg [15:0] lut;
output reg [4:0] interconnect_config_x1;
output reg [4:0] interconnect_config_x2;
output reg [4:0] interconnect_config_x3;
output reg [4:0] interconnect_config_x4;

reg [5:0] count;

initial begin
  count[5:0]=6'b000000;
  CLB_prgm_b_out=1'b0;
           i_q19 <= 0;      switch <= 0;
           i_q18 <= 0;      q15 <= 0;
           i_q17 <= 0;      q14 <= 0;
           i_q16 <= 0;      q13 <= 0;
           i_q15 <= 0;      q12 <= 0;
           i_q14 <= 0;      q11 <= 0;
           i_q13 <= 0;      q10 <= 0;
           i_q12 <= 0;      q9 <= 0;
           i_q11 <= 0;      q8 <= 0;
           i_q10 <= 0;      q7 <= 0;
           i_q9 <= 0;       q6 <= 0;
           i_q8 <= 0;       q5 <= 0;
           i_q7 <= 0;       q4 <= 0;
           i_q6 <= 0;       q3 <= 0;
           i_q5 <= 0;       q2 <= 0;
           i_q4 <= 0;       q1 <= 0;
           i_q3 <= 0;       q0 <= 0;
           i_q2 <= 0;
           i_q1 <= 0;
           i_q0 <= 0;

                                        
end

always @(posedge clk or posedge reset)
 begin
  if(prgm_b==1'b0 && CLB_prgm_b_in==1'b1 && CLB_prgm_b_out!=1'b1 && CLB_prgm_b==1'b1)  
    begin
    if(reset)
     begin
    CLB_prgm_b_out=1'b0;
    count[5:0]=6'b000000;
      end
    
    else begin
     count[5:0]=count[5:0]+1'b1; 
      if(count[5:0]==6'b100101)  //37 => 100101
      begin
      CLB_prgm_b_out= #clk 1'b1;
      count[5:0]=6'b000000;
      //prgm_b_out=1'b0;
      end  //ends
    
     end //else ends

  
  end  //first if ends

end //always block endss

always @ (posedge clk or posedge reset)
begin
  if (prgm_b==1'b0 && CLB_prgm_b_in==1'b1 && CLB_prgm_b_out!=1'b1 && CLB_prgm_b==1'b1) begin
    if(reset) begin
           i_q19 <= 0;      switch <= 0;
           i_q18 <= 0;      q15 <= 0;
           i_q17 <= 0;      q14 <= 0;
           i_q16 <= 0;      q13 <= 0;
           i_q15 <= 0;      q12 <= 0;
           i_q14 <= 0;      q11 <= 0;
           i_q13 <= 0;      q10 <= 0;
           i_q12 <= 0;      q9 <= 0;
           i_q11 <= 0;      q8 <= 0;
           i_q10 <= 0;      q7 <= 0;
           i_q9 <= 0;       q6 <= 0;
           i_q8 <= 0;       q5 <= 0;
           i_q7 <= 0;       q4 <= 0;
           i_q6 <= 0;       q3 <= 0;
           i_q5 <= 0;       q2 <= 0;
           i_q4 <= 0;       q1 <= 0;
           i_q3 <= 0;       q0 <= 0;
           i_q2 <= 0;
           i_q1 <= 0;
           i_q0 <= 0;

    end
    else begin
           i_q19 <= bit_in;     switch <= i_q0;
           i_q18 <= i_q19;      q15 <= switch;
           i_q17 <= i_q18;      q14 <= q15;
           i_q16 <= i_q17;      q13 <= q14;
           i_q15 <= i_q16;      q12 <= q13;
           i_q14 <= i_q15;      q11 <= q12;
           i_q13 <= i_q14;      q10 <= q11;
           i_q12 <= i_q13;      q9 <= q10;
           i_q11 <= i_q12;      q8 <= q9;
           i_q10 <= i_q11;      q7 <= q8;
           i_q9 <= i_q10;       q6 <= q7;
           i_q8 <= i_q9;        q5 <= q6;
           i_q7 <= i_q8;        q4 <= q5;
           i_q6 <= i_q7;        q3 <= q4;
           i_q5 <= i_q6;        q2 <= q3;
           i_q4 <= i_q5;        q1 <= q2;
           i_q3 <= i_q4;        q0 <= q1;
           i_q2 <= i_q3;      //bit_out <= q0;
           i_q1 <= i_q2;
           i_q0 <= i_q1;
       
    end
  end
end

always@(*)

begin
if(prgm_b==1'b1 && CLB_prgm_b==1'b0)
  lut[15:0]={q15,q14,q13,q12,q11,q10,q9,q8,q7,q6,q5,q4,q3,q2,q1,q0};
  
  interconnect_config_x1[4:0]={i_q4,i_q3,i_q2,i_q1,i_q0};
  interconnect_config_x2[4:0]={i_q9,i_q8,i_q7,i_q6,i_q5};
  interconnect_config_x3[4:0]={i_q14,i_q13,i_q12,i_q11,i_q10};
  interconnect_config_x4[4:0]={i_q19,i_q18,i_q17,i_q16,i_q15};
  mux_switch=switch;
end
endmodule

FPGA_dec18/testbench_CLB_config.v

module testbench_CLB_config(); 

//reg clk,reset,prgm_b,CLB_prgm_b;

reg [110:0] config_stream ;
reg bit_in_CLB;

reg CLB_prgm_b_in,prgm_b,clk,reset,CLB_prgm_b;
	//wire prgm_b_out,CLB_prgm_b_out_1,prgm_b_out_1,CLB_prgm_b_out_2,prgm_b_out_2;

wire CLB_prgm_b_out,CLB_prgm_b_out_1,CLB_prgm_b_out_2;

wire [15:0] look_up_t1;     	
wire [15:0] look_up_t2;
wire [15:0] look_up_t3;
integer counter,lut_count;
wire switch1,switch2,switch3;

wire [4:0] interconnect_a1;     wire [4:0] interconnect_b1;    //interconnect configuration bits for each inout of LUT
wire [4:0] interconnect_a2;     wire [4:0] interconnect_b2;
wire [4:0] interconnect_a3;     wire [4:0] interconnect_b3;
wire [4:0] interconnect_a4;     wire [4:0] interconnect_b4;

wire [4:0] interconnect_c1;     wire [4:0] interconnect_g1;
wire [4:0] interconnect_c2;     wire [4:0] interconnect_g2;
wire [4:0] interconnect_c3;     wire [4:0] interconnect_g3;
wire [4:0] interconnect_c4;     wire [4:0] interconnect_g4;

look_up_table_interconnect_config LUT_interconnect1(.bit_in(bit_in_CLB),.CLB_prgm_b(CLB_prgm_b),.prgm_b(prgm_b),.clk(clk),.reset(reset),.CLB_prgm_b_in(CLB_prgm_b_in),.CLB_prgm_b_out(CLB_prgm_b_out),
	.lut(look_up_t1),.interconnect_config_x1(interconnect_a1),.interconnect_config_x2(interconnect_a2),
	.interconnect_config_x3(interconnect_a3),.interconnect_config_x4(interconnect_a4),.mux_switch(switch1));

look_up_table_interconnect_config LUT_interconnect2(.bit_in(bit_in_CLB),.prgm_b(prgm_b),.clk(clk),.reset(reset),.CLB_prgm_b_in(CLB_prgm_b_out),.CLB_prgm_b_out(CLB_prgm_b_out_1),
	.lut(look_up_t2),.interconnect_config_x1(interconnect_b1),.interconnect_config_x2(interconnect_b2),
	.interconnect_config_x3(interconnect_b3),.interconnect_config_x4(interconnect_b4),.mux_switch(switch2),.CLB_prgm_b(CLB_prgm_b));

look_up_table_interconnect_config LUT_interconnect3(.bit_in(bit_in_CLB),.prgm_b(prgm_b),.clk(clk),.reset(reset),.CLB_prgm_b_in(CLB_prgm_b_out_1),.CLB_prgm_b_out(CLB_prgm_b_out_2),
	.lut(look_up_t3),.interconnect_config_x1(interconnect_c1),.interconnect_config_x2(interconnect_c2),                                
	.interconnect_config_x3(interconnect_c3),.interconnect_config_x4(interconnect_c4),.mux_switch(switch3),.CLB_prgm_b(CLB_prgm_b));  

initial begin

config_stream[110:0]= 111'b100000000000000000000000000000000000110000000000000000000000000000000000011000000000000000000000000000000000001;
clk = 1'b0;
 reset=1'b0;
 
 prgm_b=1'b1;   //indicates start of bit_stream----active low
 CLB_prgm_b=1'b0;

 fork
 #1 reset=1'b1;
 #1 prgm_b=1'b0;
 #1 CLB_prgm_b=1'b1;
  #1 CLB_prgm_b_in=1'b1;
 #1 counter=0;lut_count=0;
 #1 reset=1'b1;
 #2 reset=1'b0;
 join
end


always@(posedge clk or posedge reset)
begin 

if(prgm_b!=1'b1 && CLB_prgm_b!=1'b0) begin

	
	
    if((counter == 38) && CLB_prgm_b!=1'b0) //(no of bits required for one CLB) + 1= 37+1=38  or (37 + (number of LUT -1))
	begin
	    
		lut_count=lut_count+1;
		
		counter=0;
		if(lut_count==3)
		begin
			
			CLB_prgm_b=1'b0;
            prgm_b=1'b1;
			
		end
	end 
	bit_in_CLB <= config_stream[0];
	config_stream <=config_stream>>1;
	counter=counter+1;//if endsj
end 

end //always block ends

initial begin

forever #5 clk=!clk;
end

initial
	begin 

	#6350;               //time=5 seconds


	reset=1'b0;


	#20500 $finish;
end

initial begin
    $dumpfile("test.vcd");
    $dumpvars(0,testbench_CLB_config);
    $timeformat(-9, 1, " ns", 6);
	$monitor("At t=%t prgm_b=%b reset=%b lut_count=%d bit_in_CLB=%b counter=%d",$time,prgm_b,reset,lut_count,bit_in_CLB,counter);
end

//Stimulus

endmodule

New Version/FPGA_withLoop/test_dummy/Config_methods/M1/test.vcd
$date
	Fri Dec 09 01:55:46 2016
$end
$version
	Icarus Verilog
$end
$timescale
	1s
$end
$scope module testbench_CLB_config $end
$var wire 1 ! switch3 $end
$var wire 1 " switch2 $end
$var wire 1 # switch1 $end
$var wire 16 $ look_up_t3 [15:0] $end
$var wire 16 % look_up_t2 [15:0] $end
$var wire 16 & look_up_t1 [15:0] $end
$var wire 5 ' interconnect_c4 [4:0] $end
$var wire 5 ( interconnect_c3 [4:0] $end
$var wire 5 ) interconnect_c2 [4:0] $end
$var wire 5 * interconnect_c1 [4:0] $end
$var wire 5 + interconnect_b4 [4:0] $end
$var wire 5 , interconnect_b3 [4:0] $end
$var wire 5 - interconnect_b2 [4:0] $end
$var wire 5 . interconnect_b1 [4:0] $end
$var wire 5 / interconnect_a4 [4:0] $end
$var wire 5 0 interconnect_a3 [4:0] $end
$var wire 5 1 interconnect_a2 [4:0] $end
$var wire 5 2 interconnect_a1 [4:0] $end
$var wire 1 3 CLB_prgm_b_out_2 $end
$var wire 1 4 CLB_prgm_b_out_1 $end
$var wire 1 5 CLB_prgm_b_out $end
$var reg 1 6 CLB_prgm_b $end
$var reg 1 7 CLB_prgm_b_in $end
$var reg 1 8 bit_in_CLB $end
$var reg 1 9 clk $end
$var reg 111 : config_stream [110:0] $end
$var reg 1 ; prgm_b $end
$var reg 1 < reset $end
$var integer 32 = counter [31:0] $end
$var integer 32 > lut_count [31:0] $end
$scope module LUT_interconnect1 $end
$var wire 1 6 CLB_prgm_b $end
$var wire 1 7 CLB_prgm_b_in $end
$var wire 1 8 bit_in $end
$var wire 1 9 clk $end
$var wire 1 ; prgm_b $end
$var wire 1 < reset $end
$var reg 1 5 CLB_prgm_b_out $end
$var reg 6 ? count [5:0] $end
$var reg 1 @ i_q0 $end
$var reg 1 A i_q1 $end
$var reg 1 B i_q10 $end
$var reg 1 C i_q11 $end
$var reg 1 D i_q12 $end
$var reg 1 E i_q13 $end
$var reg 1 F i_q14 $end
$var reg 1 G i_q15 $end
$var reg 1 H i_q16 $end
$var reg 1 I i_q17 $end
$var reg 1 J i_q18 $end
$var reg 1 K i_q19 $end
$var reg 1 L i_q2 $end
$var reg 1 M i_q3 $end
$var reg 1 N i_q4 $end
$var reg 1 O i_q5 $end
$var reg 1 P i_q6 $end
$var reg 1 Q i_q7 $end
$var reg 1 R i_q8 $end
$var reg 1 S i_q9 $end
$var reg 5 T interconnect_config_x1 [4:0] $end
$var reg 5 U interconnect_config_x2 [4:0] $end
$var reg 5 V interconnect_config_x3 [4:0] $end
$var reg 5 W interconnect_config_x4 [4:0] $end
$var reg 16 X lut [15:0] $end
$var reg 1 # mux_switch $end
$var reg 1 Y q0 $end
$var reg 1 Z q1 $end
$var reg 1 [ q10 $end
$var reg 1 \ q11 $end
$var reg 1 ] q12 $end
$var reg 1 ^ q13 $end
$var reg 1 _ q14 $end
$var reg 1 ` q15 $end
$var reg 1 a q2 $end
$var reg 1 b q3 $end
$var reg 1 c q4 $end
$var reg 1 d q5 $end
$var reg 1 e q6 $end
$var reg 1 f q7 $end
$var reg 1 g q8 $end
$var reg 1 h q9 $end
$var reg 1 i switch $end
$upscope $end
$scope module LUT_interconnect2 $end
$var wire 1 6 CLB_prgm_b $end
$var wire 1 5 CLB_prgm_b_in $end
$var wire 1 8 bit_in $end
$var wire 1 9 clk $end
$var wire 1 ; prgm_b $end
$var wire 1 < reset $end
$var reg 1 4 CLB_prgm_b_out $end
$var reg 6 j count [5:0] $end
$var reg 1 k i_q0 $end
$var reg 1 l i_q1 $end
$var reg 1 m i_q10 $end
$var reg 1 n i_q11 $end
$var reg 1 o i_q12 $end
$var reg 1 p i_q13 $end
$var reg 1 q i_q14 $end
$var reg 1 r i_q15 $end
$var reg 1 s i_q16 $end
$var reg 1 t i_q17 $end
$var reg 1 u i_q18 $end
$var reg 1 v i_q19 $end
$var reg 1 w i_q2 $end
$var reg 1 x i_q3 $end
$var reg 1 y i_q4 $end
$var reg 1 z i_q5 $end
$var reg 1 { i_q6 $end
$var reg 1 | i_q7 $end
$var reg 1 } i_q8 $end
$var reg 1 ~ i_q9 $end
$var reg 5 !" interconnect_config_x1 [4:0] $end
$var reg 5 "" interconnect_config_x2 [4:0] $end
$var reg 5 #" interconnect_config_x3 [4:0] $end
$var reg 5 $" interconnect_config_x4 [4:0] $end
$var reg 16 %" lut [15:0] $end
$var reg 1 " mux_switch $end
$var reg 1 &" q0 $end
$var reg 1 '" q1 $end
$var reg 1 (" q10 $end
$var reg 1 )" q11 $end
$var reg 1 *" q12 $end
$var reg 1 +" q13 $end
$var reg 1 ," q14 $end
$var reg 1 -" q15 $end
$var reg 1 ." q2 $end
$var reg 1 /" q3 $end
$var reg 1 0" q4 $end
$var reg 1 1" q5 $end
$var reg 1 2" q6 $end
$var reg 1 3" q7 $end
$var reg 1 4" q8 $end
$var reg 1 5" q9 $end
$var reg 1 6" switch $end
$upscope $end
$scope module LUT_interconnect3 $end
$var wire 1 6 CLB_prgm_b $end
$var wire 1 4 CLB_prgm_b_in $end
$var wire 1 8 bit_in $end
$var wire 1 9 clk $end
$var wire 1 ; prgm_b $end
$var wire 1 < reset $end
$var reg 1 3 CLB_prgm_b_out $end
$var reg 6 7" count [5:0] $end
$var reg 1 8" i_q0 $end
$var reg 1 9" i_q1 $end
$var reg 1 :" i_q10 $end
$var reg 1 ;" i_q11 $end
$var reg 1 <" i_q12 $end
$var reg 1 =" i_q13 $end
$var reg 1 >" i_q14 $end
$var reg 1 ?" i_q15 $end
$var reg 1 @" i_q16 $end
$var reg 1 A" i_q17 $end
$var reg 1 B" i_q18 $end
$var reg 1 C" i_q19 $end
$var reg 1 D" i_q2 $end
$var reg 1 E" i_q3 $end
$var reg 1 F" i_q4 $end
$var reg 1 G" i_q5 $end
$var reg 1 H" i_q6 $end
$var reg 1 I" i_q7 $end
$var reg 1 J" i_q8 $end
$var reg 1 K" i_q9 $end
$var reg 5 L" interconnect_config_x1 [4:0] $end
$var reg 5 M" interconnect_config_x2 [4:0] $end
$var reg 5 N" interconnect_config_x3 [4:0] $end
$var reg 5 O" interconnect_config_x4 [4:0] $end
$var reg 16 P" lut [15:0] $end
$var reg 1 ! mux_switch $end
$var reg 1 Q" q0 $end
$var reg 1 R" q1 $end
$var reg 1 S" q10 $end
$var reg 1 T" q11 $end
$var reg 1 U" q12 $end
$var reg 1 V" q13 $end
$var reg 1 W" q14 $end
$var reg 1 X" q15 $end
$var reg 1 Y" q2 $end
$var reg 1 Z" q3 $end
$var reg 1 [" q4 $end
$var reg 1 \" q5 $end
$var reg 1 ]" q6 $end
$var reg 1 ^" q7 $end
$var reg 1 _" q8 $end
$var reg 1 `" q9 $end
$var reg 1 a" switch $end
$upscope $end
$upscope $end
$enddefinitions $end
#0
$dumpvars
0a"
0`"
0_"
0^"
0]"
0\"
0["
0Z"
0Y"
0X"
0W"
0V"
0U"
0T"
0S"
0R"
0Q"
b0 P"
b0 O"
b0 N"
b0 M"
b0 L"
0K"
0J"
0I"
0H"
0G"
0F"
0E"
0D"
0C"
0B"
0A"
0@"
0?"
0>"
0="
0<"
0;"
0:"
09"
08"
b0 7"
06"
05"
04"
03"
02"
01"
00"
0/"
0."
0-"
0,"
0+"
0*"
0)"
0("
0'"
0&"
b0 %"
b0 $"
b0 #"
b0 ""
b0 !"
0~
0}
0|
0{
0z
0y
0x
0w
0v
0u
0t
0s
0r
0q
0p
0o
0n
0m
0l
0k
b0 j
0i
0h
0g
0f
0e
0d
0c
0b
0a
0`
0_
0^
0]
0\
0[
0Z
0Y
b0 X
b0 W
b0 V
b0 U
b0 T
0S
0R
0Q
0P
0O
0N
0M
0L
0K
0J
0I
0H
0G
0F
0E
0D
0C
0B
0A
0@
b0 ?
b0 >
bx =
0<
1;
b100000000000000000000000000000000000110000000000000000000000000000000000011000000000000000000000000000000000001 :
09
x8
x7
06
05
04
03
b0 2
b0 1
b0 0
b0 /
b0 .
b0 -
b0 ,
b0 +
b0 *
b0 )
b0 (
b0 '
b0 &
b0 %
b0 $
0#
0"
0!
$end
#1
b10000000000000000000000000000000000011000000000000000000000000000000000001100000000000000000000000000000000000 :
18
0;
16
17
b1 =
1<
#2
0<
#5
b10000 /
b10000 W
b1000000000000000000000000000000000001100000000000000000000000000000000000110000000000000000000000000000000000 :
08
1K
b10 =
b1 ?
19
#10
09
#15
b1000 /
b1000 W
1J
0K
b100000000000000000000000000000000000110000000000000000000000000000000000011000000000000000000000000000000000 :
b10 ?
b11 =
19
#20
09
#25
b100 /
b100 W
b10000000000000000000000000000000000011000000000000000000000000000000000001100000000000000000000000000000000 :
1I
0J
b100 =
b11 ?
19
#30
09
#35
b10 /
b10 W
1H
0I
b1000000000000000000000000000000000001100000000000000000000000000000000000110000000000000000000000000000000 :
b100 ?
b101 =
19
#40
09
#45
b1 /
b1 W
b100000000000000000000000000000000000110000000000000000000000000000000000011000000000000000000000000000000 :
1G
0H
b110 =
b101 ?
19
#50
09
#55
b0 /
b0 W
b10000 0
b10000 V
1F
0G
b10000000000000000000000000000000000011000000000000000000000000000000000001100000000000000000000000000000 :
b110 ?
b111 =
19
#60
09
#65
b1000 0
b1000 V
b1000000000000000000000000000000000001100000000000000000000000000000000000110000000000000000000000000000 :
1E
0F
b1000 =
b111 ?
19
#70
09
#75
b100 0
b100 V
1D
0E
b100000000000000000000000000000000000110000000000000000000000000000000000011000000000000000000000000000 :
b1000 ?
b1001 =
19
#80
09
#85
b10 0
b10 V
b10000000000000000000000000000000000011000000000000000000000000000000000001100000000000000000000000000 :
1C
0D
b1010 =
b1001 ?
19
#90
09
#95
b1 0
b1 V
1B
0C
b1000000000000000000000000000000000001100000000000000000000000000000000000110000000000000000000000000 :
b1010 ?
b1011 =
19
#100
09
#105
b0 0
b0 V
b10000 1
b10000 U
b100000000000000000000000000000000000110000000000000000000000000000000000011000000000000000000000000 :
1S
0B
b1100 =
b1011 ?
19
#110
09
#115
b1000 1
b1000 U
1R
0S
b10000000000000000000000000000000000011000000000000000000000000000000000001100000000000000000000000 :
b1100 ?
b1101 =
19
#120
09
#125
b100 1
b100 U
b1000000000000000000000000000000000001100000000000000000000000000000000000110000000000000000000000 :
1Q
0R
b1110 =
b1101 ?
19
#130
09
#135
b10 1
b10 U
1P
0Q
b100000000000000000000000000000000000110000000000000000000000000000000000011000000000000000000000 :
b1110 ?
b1111 =
19
#140
09
#145
b1 1
b1 U
b10000000000000000000000000000000000011000000000000000000000000000000000001100000000000000000000 :
1O
0P
b10000 =
b1111 ?
19
#150
09
#155
b0 1
b0 U
b10000 2
b10000 T
1N
0O
b1000000000000000000000000000000000001100000000000000000000000000000000000110000000000000000000 :
b10000 ?
b10001 =
19
#160
09
#165
b1000 2
b1000 T
b100000000000000000000000000000000000110000000000000000000000000000000000011000000000000000000 :
1M
0N
b10010 =
b10001 ?
19
#170
09
#175
b100 2
b100 T
1L
0M
b10000000000000000000000000000000000011000000000000000000000000000000000001100000000000000000 :
b10010 ?
b10011 =
19
#180
09
#185
b10 2
b10 T
b1000000000000000000000000000000000001100000000000000000000000000000000000110000000000000000 :
1A
0L
b10100 =
b10011 ?
19
#190
09
#195
b1 2
b1 T
1@
0A
b100000000000000000000000000000000000110000000000000000000000000000000000011000000000000000 :
b10100 ?
b10101 =
19
#200
09
#205
1#
b0 2
b0 T
b10000000000000000000000000000000000011000000000000000000000000000000000001100000000000000 :
0@
1i
b10110 =
b10101 ?
19
#210
09
#215
0#
1`
0i
b1000000000000000000000000000000000001100000000000000000000000000000000000110000000000000 :
b10110 ?
b10111 =
19
#220
09
#225
b100000000000000000000000000000000000110000000000000000000000000000000000011000000000000 :
1_
0`
b11000 =
b10111 ?
19
#230
09
#235
1^
0_
b10000000000000000000000000000000000011000000000000000000000000000000000001100000000000 :
b11000 ?
b11001 =
19
#240
09
#245
b1000000000000000000000000000000000001100000000000000000000000000000000000110000000000 :
1]
0^
b11010 =
b11001 ?
19
#250
09
#255
1\
0]
b100000000000000000000000000000000000110000000000000000000000000000000000011000000000 :
b11010 ?
b11011 =
19
#260
09
#265
b10000000000000000000000000000000000011000000000000000000000000000000000001100000000 :
1[
0\
b11100 =
b11011 ?
19
#270
09
#275
1h
0[
b1000000000000000000000000000000000001100000000000000000000000000000000000110000000 :
b11100 ?
b11101 =
19
#280
09
#285
b100000000000000000000000000000000000110000000000000000000000000000000000011000000 :
1g
0h
b11110 =
b11101 ?
19
#290
09
#295
1f
0g
b10000000000000000000000000000000000011000000000000000000000000000000000001100000 :
b11110 ?
b11111 =
19
#300
09
#305
b1000000000000000000000000000000000001100000000000000000000000000000000000110000 :
1e
0f
b100000 =
b11111 ?
19
#310
09
#315
1d
0e
b100000000000000000000000000000000000110000000000000000000000000000000000011000 :
b100000 ?
b100001 =
19
#320
09
#325
b10000000000000000000000000000000000011000000000000000000000000000000000001100 :
1c
0d
b100010 =
b100001 ?
19
#330
09
#335
1b
0c
b1000000000000000000000000000000000001100000000000000000000000000000000000110 :
b100010 ?
b100011 =
19
#340
09
#345
b100000000000000000000000000000000000110000000000000000000000000000000000011 :
1a
0b
b100100 =
b100011 ?
19
#350
09
#355
1Z
0a
b10000000000000000000000000000000000011000000000000000000000000000000000001 :
18
b100100 ?
b100101 =
19
#360
09
#365
b10000 /
b10000 W
b1000000000000000000000000000000000001100000000000000000000000000000000000 :
1Y
0Z
1K
b100110 =
b100101 ?
19
#370
09
#375
b11000 /
b11000 W
0Y
1J
b100000000000000000000000000000000000110000000000000000000000000000000000 :
08
15
b0 ?
b1 =
b1 >
19
#380
09
#385
b10000000000000000000000000000000000011000000000000000000000000000000000 :
b10 =
b1 j
19
#390
09
#395
b1000000000000000000000000000000000001100000000000000000000000000000000 :
b10 j
b11 =
19
#400
09
#405
b100000000000000000000000000000000000110000000000000000000000000000000 :
b100 =
b11 j
19
#410
09
#415
b10000000000000000000000000000000000011000000000000000000000000000000 :
b100 j
b101 =
19
#420
09
#425
b1000000000000000000000000000000000001100000000000000000000000000000 :
b110 =
b101 j
19
#430
09
#435
b100000000000000000000000000000000000110000000000000000000000000000 :
b110 j
b111 =
19
#440
09
#445
b10000000000000000000000000000000000011000000000000000000000000000 :
b1000 =
b111 j
19
#450
09
#455
b1000000000000000000000000000000000001100000000000000000000000000 :
b1000 j
b1001 =
19
#460
09
#465
b100000000000000000000000000000000000110000000000000000000000000 :
b1010 =
b1001 j
19
#470
09
#475
b10000000000000000000000000000000000011000000000000000000000000 :
b1010 j
b1011 =
19
#480
09
#485
b1000000000000000000000000000000000001100000000000000000000000 :
b1100 =
b1011 j
19
#490
09
#495
b100000000000000000000000000000000000110000000000000000000000 :
b1100 j
b1101 =
19
#500
09
#505
b10000000000000000000000000000000000011000000000000000000000 :
b1110 =
b1101 j
19
#510
09
#515
b1000000000000000000000000000000000001100000000000000000000 :
b1110 j
b1111 =
19
#520
09
#525
b100000000000000000000000000000000000110000000000000000000 :
b10000 =
b1111 j
19
#530
09
#535
b10000000000000000000000000000000000011000000000000000000 :
b10000 j
b10001 =
19
#540
09
#545
b1000000000000000000000000000000000001100000000000000000 :
b10010 =
b10001 j
19
#550
09
#555
b100000000000000000000000000000000000110000000000000000 :
b10010 j
b10011 =
19
#560
09
#565
b10000000000000000000000000000000000011000000000000000 :
b10100 =
b10011 j
19
#570
09
#575
b1000000000000000000000000000000000001100000000000000 :
b10100 j
b10101 =
19
#580
09
#585
b100000000000000000000000000000000000110000000000000 :
b10110 =
b10101 j
19
#590
09
#595
b10000000000000000000000000000000000011000000000000 :
b10110 j
b10111 =
19
#600
09
#605
b1000000000000000000000000000000000001100000000000 :
b11000 =
b10111 j
19
#610
09
#615
b100000000000000000000000000000000000110000000000 :
b11000 j
b11001 =
19
#620
09
#625
b10000000000000000000000000000000000011000000000 :
b11010 =
b11001 j
19
#630
09
#635
b1000000000000000000000000000000000001100000000 :
b11010 j
b11011 =
19
#640
09
#645
b100000000000000000000000000000000000110000000 :
b11100 =
b11011 j
19
#650
09
#655
b10000000000000000000000000000000000011000000 :
b11100 j
b11101 =
19
#660
09
#665
b1000000000000000000000000000000000001100000 :
b11110 =
b11101 j
19
#670
09
#675
b100000000000000000000000000000000000110000 :
b11110 j
b11111 =
19
#680
09
#685
b10000000000000000000000000000000000011000 :
b100000 =
b11111 j
19
#690
09
#695
b1000000000000000000000000000000000001100 :
b100000 j
b100001 =
19
#700
09
#705
b100000000000000000000000000000000000110 :
b100010 =
b100001 j
19
#710
09
#715
b10000000000000000000000000000000000011 :
b100010 j
b100011 =
19
#720
09
#725
b1000000000000000000000000000000000001 :
18
b100100 =
b100011 j
19
#730
09
#735
b10000 +
b10000 $"
1v
b100000000000000000000000000000000000 :
b100100 j
b100101 =
19
#740
09
#745
b11000 +
b11000 $"
b10000000000000000000000000000000000 :
08
1u
b100110 =
b100101 j
19
#750
09
#755
b1100 +
b1100 $"
1t
0v
b1000000000000000000000000000000000 :
14
b0 j
b1 =
b10 >
19
#760
09
#765
b100000000000000000000000000000000 :
b10 =
b1 7"
19
#770
09
#775
b10000000000000000000000000000000 :
b10 7"
b11 =
19
#780
09
#785
b1000000000000000000000000000000 :
b100 =
b11 7"
19
#790
09
#795
b100000000000000000000000000000 :
b100 7"
b101 =
19
#800
09
#805
b10000000000000000000000000000 :
b110 =
b101 7"
19
#810
09
#815
b1000000000000000000000000000 :
b110 7"
b111 =
19
#820
09
#825
b100000000000000000000000000 :
b1000 =
b111 7"
19
#830
09
#835
b10000000000000000000000000 :
b1000 7"
b1001 =
19
#840
09
#845
b1000000000000000000000000 :
b1010 =
b1001 7"
19
#850
09
#855
b100000000000000000000000 :
b1010 7"
b1011 =
19
#860
09
#865
b10000000000000000000000 :
b1100 =
b1011 7"
19
#870
09
#875
b1000000000000000000000 :
b1100 7"
b1101 =
19
#880
09
#885
b100000000000000000000 :
b1110 =
b1101 7"
19
#890
09
#895
b10000000000000000000 :
b1110 7"
b1111 =
19
#900
09
#905
b1000000000000000000 :
b10000 =
b1111 7"
19
#910
09
#915
b100000000000000000 :
b10000 7"
b10001 =
19
#920
09
#925
b10000000000000000 :
b10010 =
b10001 7"
19
#930
09
#935
b1000000000000000 :
b10010 7"
b10011 =
19
#940
09
#945
b100000000000000 :
b10100 =
b10011 7"
19
#950
09
#955
b10000000000000 :
b10100 7"
b10101 =
19
#960
09
#965
b1000000000000 :
b10110 =
b10101 7"
19
#970
09
#975
b100000000000 :
b10110 7"
b10111 =
19
#980
09
#985
b10000000000 :
b11000 =
b10111 7"
19
#990
09
#995
b1000000000 :
b11000 7"
b11001 =
19
#1000
09
#1005
b100000000 :
b11010 =
b11001 7"
19
#1010
09
#1015
b10000000 :
b11010 7"
b11011 =
19
#1020
09
#1025
b1000000 :
b11100 =
b11011 7"
19
#1030
09
#1035
b100000 :
b11100 7"
b11101 =
19
#1040
09
#1045
b10000 :
b11110 =
b11101 7"
19
#1050
09
#1055
b1000 :
b11110 7"
b11111 =
19
#1060
09
#1065
b100 :
b100000 =
b11111 7"
19
#1070
09
#1075
b10 :
b100000 7"
b100001 =
19
#1080
09
#1085
b1 :
b100010 =
b100001 7"
19
#1090
09
#1095
b0 :
18
b100010 7"
b100011 =
19
#1100
09
#1105
b10000 '
b10000 O"
08
1C"
b100100 =
b100011 7"
19
#1110
09
#1115
b1000 '
b1000 O"
1B"
0C"
b100100 7"
b100101 =
19
#1120
09
#1125
b100 '
b100 O"
1A"
0B"
b100110 =
b100101 7"
19
#1130
09
#1135
1;
06
b1 =
b11 >
19
